flask_nsfw.py
setup.py
util.py
Flask_NSFW.egg-info/PKG-INFO
Flask_NSFW.egg-info/SOURCES.txt
Flask_NSFW.egg-info/dependency_links.txt
Flask_NSFW.egg-info/not-zip-safe
Flask_NSFW.egg-info/requires.txt
Flask_NSFW.egg-info/top_level.txt