Metadata-Version: 1.1
Name: Flask-NSFW
Version: 6
Summary: Flask-NSFW blocks all the requests that contains images with nudity.
Home-page: UNKNOWN
Author: smit thakkar
Author-email: smitthakkar96@gmail.com
License: BSD
Platform: any
Classifier: Environment :: Web Environment
Classifier: Intended Audience :: Developers
Classifier: License :: OSI Approved :: BSD License
Classifier: Operating System :: OS Independent
Classifier: Programming Language :: Python
Classifier: Topic :: Internet :: WWW/HTTP :: Dynamic Content
Classifier: Topic :: Software Development :: Libraries :: Python Modules
